CHANGELOG.txt
LICENSE.txt
MANIFEST.in
README.txt
setup.py
secretListing/__init__.py
secretListing.egg-info/PKG-INFO
secretListing.egg-info/SOURCES.txt
secretListing.egg-info/dependency_links.txt
secretListing.egg-info/top_level.txt