Metadata-Version: 1.1
Name: secretListing
Version: 0.0.1
Summary: Makes operations on lists easy.
Home-page: UNKNOWN
Author: Damian Czapla
Author-email: damianczapla121212@gmail.com
License: UNKNOWN
Keywords: secret
Platform: UNKNOWN
Classifier: Development Status :: 5 - Production/Stable
Classifier: Intended Audience :: Education
Classifier: Operating System :: Microsoft :: Windows :: Windows 10
Classifier: License :: OSI Approved :: MIT License
Classifier: Programming Language :: Python :: 3
